{"config": {"view": {"continuousWidth": 300, "continuousHeight": 300}}, "layer": [{"mark": {"type": "bar"}, "encoding": {"color": {"field": "Attacking Type", "scale": {"domain": ["Dribbles", "Touches in Opp Box"], "range": ["#08bd14", "#bd2308"]}, "type": "nominal"}, "tooltip": [{"field": "Player", "title": "Player Name", "type": "nominal"}, {"field": "Attacking Type", "title": "Attacking Type", "type": "nominal"}, {"field": "Count", "title": "Total", "type": "quantitative"}], "x": {"field": "Player", "sort": ["Kyreece Lisbie"], "type": "nominal"}, "xOffset": {"field": "Attacking Type", "type": "nominal"}, "y": {"aggregate": "sum", "field": "Count", "title": "Attacking", "type": "quantitative"}}}, {"mark": {"type": "text", "align": "center", "dy": -10, "size": 17}, "encoding": {"color": {"field": "Attacking Type", "scale": {"domain": ["Dribbles", "Touches in Opp Box"], "range": ["#08bd14", "#bd2308"]}, "type": "nominal"}, "text": {"aggregate": "sum", "field": "Count", "type": "quantitative"}, "tooltip": [{"field": "Player", "title": "Player Name", "type": "nominal"}, {"field": "Attacking Type", "title": "Attacking Type", "type": "nominal"}, {"field": "Count", "title": "Total", "type": "quantitative"}], "x": {"field": "Player", "sort": ["Kyreece Lisbie"], "type": "nominal"}, "xOffset": {"field": "Attacking Type", "type": "nominal"}, "y": {"aggregate": "sum", "field": "Count", "type": "quantitative"}}}], "data": {"name": "data-654482d30e7b75ba7359eda1c56a2ab6"}, "height": 800, "width": 500, "$schema": "https://vega.github.io/schema/vega-lite/v6.4.1.json", "datasets": {"data-654482d30e7b75ba7359eda1c56a2ab6": [{"Player": "Kyreece Lisbie", "Attacking Type": "Dribbles", "Count": 38}, {"Player": "Harry Anderson", "Attacking Type": "Dribbles", "Count": 32}, {"Player": "Calum Agius", "Attacking Type": "Dribbles", "Count": 10}, {"Player": "Kyreece Lisbie", "Attacking Type": "Touches in Opp Box", "Count": 201}, {"Player": "Harry Anderson", "Attacking Type": "Touches in Opp Box", "Count": 112}, {"Player": "Calum Agius", "Attacking Type": "Touches in Opp Box", "Count": 64}]}}